<?xml version="1.0" encoding="UTF-8"?>
<!DOCTYPE mapper PUBLIC "-//mybatis.org//DTD Mapper 3.0//EN" "http://mybatis.org/dtd/mybatis-3-mapper.dtd">
<mapper namespace="com.lemarket.data.dao.TokenMapper">
  <resultMap id="BaseResultMap" type="com.lemarket.data.model.Token">
    <!--
      WARNING - @mbg.generated
      This element is automatically generated by MyBatis Generator, do not modify.
    -->
    <result column="id" jdbcType="INTEGER" property="id" />
    <result column="token" jdbcType="VARCHAR" property="token" />
    <result column="date_create" jdbcType="TIMESTAMP" property="dateCreate" />
    <result column="validity" jdbcType="INTEGER" property="validity" />
  </resultMap>
  <insert id="insert" parameterType="com.lemarket.data.model.Token">
    <!--
      WARNING - @mbg.generated
      This element is automatically generated by MyBatis Generator, do not modify.
    -->
    insert into Token (id, token, date_create, 
      validity)
    values (#{id,jdbcType=INTEGER}, #{token,jdbcType=VARCHAR}, #{dateCreate,jdbcType=TIMESTAMP}, 
      #{validity,jdbcType=INTEGER})
  </insert>
  <delete id="deleteById">
    DELETE FROM Token WHERE id = #{id};
  </delete>
  <select id="selectAll" resultMap="BaseResultMap">
    <!--
      WARNING - @mbg.generated
      This element is automatically generated by MyBatis Generator, do not modify.
    -->
    select id, token, date_create, validity
    from Token
  </select>
    <select id="selectById" resultMap="BaseResultMap">
        SELECT * FROM Token WHERE id = #{id};
    </select>
  <select id="selectByToken" resultMap="BaseResultMap">
    SELECT * FROM Token WHERE token = #{token};
  </select>
  <select id="selectUserById" resultMap="BaseResultMap">
    SELECT Users.id FROM Users WHERE id = #{id}
  </select>
</mapper>